hyperbuild/__init__.py
hyperbuild/linux-x86_64-3_5/hyperbuild.so
hyperbuild/linux-x86_64-3_6/hyperbuild.so
hyperbuild/linux-x86_64-3_7/hyperbuild.so
hyperbuild/linux-x86_64-3_8/hyperbuild.so
hyperbuild/macos-x86_64-3_5/hyperbuild.so
hyperbuild/macos-x86_64-3_6/hyperbuild.so
hyperbuild/macos-x86_64-3_7/hyperbuild.so
hyperbuild/macos-x86_64-3_8/hyperbuild.so
hyperbuild-0.2.4.dist-info/METADATA
hyperbuild-0.2.4.dist-info/WHEEL
hyperbuild-0.2.4.dist-info/top_level.txt
hyperbuild-0.2.4.dist-info/RECORD
