Metadata-Version: 2.1
Name: hyperbuild
Version: 0.2.4
Summary: Fast allocation-less HTML minifier with smart whitespace handling
Home-page: https://github.com/wilsonzlin/hyperbuild
Author: Wilson Lin
Author-email: code@wilsonl.in
License: UNKNOWN
Platform: UNKNOWN
Classifier: Programming Language :: Python :: 3 :: Only
Classifier: Programming Language :: Python :: Implementation :: CPython
Classifier: License :: OSI Approved :: MIT License
Classifier: Operating System :: OS Independent
Requires-Python: >=3.5
